gprime/__init__.py
gprime/config.py
gprime/const.py
gprime/constfunc.py
gprime/dbstate.py
gprime/errors.py
gprime/git_revision.py
gprime/relationship.py
gprime/sort.py
gprime/updatecallback.py
gprime/user.py
gprime/version.py
gprime/app/__init__.py
gprime/app/__main__.py
gprime/app/app.py
gprime/app/dictionarydb.py
gprime/app/passman.py
gprime/app/template_functions.py
gprime/app/forms/__init__.py
gprime/app/forms/actionform.py
gprime/app/forms/citationform.py
gprime/app/forms/eventform.py
gprime/app/forms/familyform.py
gprime/app/forms/forms.py
gprime/app/forms/mediaform.py
gprime/app/forms/noteform.py
gprime/app/forms/personform.py
gprime/app/forms/placeform.py
gprime/app/forms/repositoryform.py
gprime/app/forms/sourceform.py
gprime/app/forms/tagform.py
gprime/app/handlers/__init__.py
gprime/app/handlers/actionhandler.py
gprime/app/handlers/citationhandler.py
gprime/app/handlers/deletehandler.py
gprime/app/handlers/eventhandler.py
gprime/app/handlers/familyhandler.py
gprime/app/handlers/handlers.py
gprime/app/handlers/imagehandler.py
gprime/app/handlers/jsonhandler.py
gprime/app/handlers/mediahandler.py
gprime/app/handlers/notehandler.py
gprime/app/handlers/personhandler.py
gprime/app/handlers/placehandler.py
gprime/app/handlers/repositoryhandler.py
gprime/app/handlers/sourcehandler.py
gprime/app/handlers/taghandler.py
gprime/cli/__init__.py
gprime/cli/arghandler.py
gprime/cli/argparser.py
gprime/cli/clidbman.py
gprime/cli/grampscli.py
gprime/cli/user.py
gprime/cli/plug/__init__.py
gprime/cli/test/__init__.py
gprime/cli/test/argparser_test.py
gprime/cli/test/cli_test.py
gprime/datehandler/__init__.py
gprime/datehandler/_date_ar.py
gprime/datehandler/_date_bg.py
gprime/datehandler/_date_ca.py
gprime/datehandler/_date_cs.py
gprime/datehandler/_date_da.py
gprime/datehandler/_date_de.py
gprime/datehandler/_date_el.py
gprime/datehandler/_date_es.py
gprime/datehandler/_date_fi.py
gprime-0.0.5.data/data/share/mime-info/gramps.keys
gprime-0.0.5.dist-info/DESCRIPTION.rst
gprime-0.0.5.dist-info/METADATA
gprime-0.0.5.dist-info/RECORD
gprime-0.0.5.dist-info/WHEEL
gprime-0.0.5.dist-info/entry_points.txt
gprime-0.0.5.dist-info/metadata.json
gprime-0.0.5.dist-info/top_level.txt
