Metadata-Version: 2.0
Name: gprime
Version: 0.0.5
Summary: gPrime webapp for genealogy
Home-page: https://github.com/GenealogyCollective/gprime
Author: Doug Blank
Author-email: doug.blank@gmail.org
License: UNKNOWN
Platform: UNKNOWN
Classifier: Environment :: Web Environment
Classifier: License :: OSI Approved :: GNU General Public License v2 (GPLv2)
Classifier: Programming Language :: Python :: 3
Classifier: Topic :: Sociology :: Genealogy
Requires-Dist: meta
Requires-Dist: passlib
Requires-Dist: pillow
Requires-Dist: simplejson
Requires-Dist: tornado
